crypteia/__init__.py
crypteia/multibasing.py
crypteia/multihashing.py
crypteia-1.0.1.dist-info/LICENSE
crypteia-1.0.1.dist-info/METADATA
crypteia-1.0.1.dist-info/WHEEL
crypteia-1.0.1.dist-info/top_level.txt
crypteia-1.0.1.dist-info/RECORD
