Metadata-Version: 2.1
Name: crypteia
Version: 1.0.1
Summary: Cryptographer's content-addressing companion.
Author: Nei Cardoso de Oliveira Neto
Author-email: nei@teialabs.com
Requires-Python: >=3.11
License-File: LICENSE
Requires-Dist: multiformats
